MANIFEST.in
README.md
README.txt
setup.py
django_foundation.egg-info/PKG-INFO
django_foundation.egg-info/SOURCES.txt
django_foundation.egg-info/dependency_links.txt
django_foundation.egg-info/not-zip-safe
django_foundation.egg-info/top_level.txt
foundation/__init__.py
foundation/urls.py
foundation/static/foundation/images/.DS_Store
foundation/static/foundation/images/foundation/.DS_Store
foundation/static/foundation/images/foundation/orbit/bullets.jpg
foundation/static/foundation/images/foundation/orbit/left-arrow-small.png
foundation/static/foundation/images/foundation/orbit/left-arrow.png
foundation/static/foundation/images/foundation/orbit/loading.gif
foundation/static/foundation/images/foundation/orbit/mask-black.png
foundation/static/foundation/images/foundation/orbit/pause-black.png
foundation/static/foundation/images/foundation/orbit/right-arrow-small.png
foundation/static/foundation/images/foundation/orbit/right-arrow.png
foundation/static/foundation/images/foundation/orbit/rotator-black.png
foundation/static/foundation/images/foundation/orbit/timer-black.png
foundation/static/foundation/javascripts/app.js
foundation/static/foundation/javascripts/foundation.min.js
foundation/static/foundation/javascripts/jquery.foundation.accordion.js
foundation/static/foundation/javascripts/jquery.foundation.alerts.js
foundation/static/foundation/javascripts/jquery.foundation.buttons.js
foundation/static/foundation/javascripts/jquery.foundation.clearing.js
foundation/static/foundation/javascripts/jquery.foundation.forms.js
foundation/static/foundation/javascripts/jquery.foundation.joyride.js
foundation/static/foundation/javascripts/jquery.foundation.magellan.js
foundation/static/foundation/javascripts/jquery.foundation.mediaQueryToggle.js
foundation/static/foundation/javascripts/jquery.foundation.navigation.js
foundation/static/foundation/javascripts/jquery.foundation.orbit.js
foundation/static/foundation/javascripts/jquery.foundation.reveal.js
foundation/static/foundation/javascripts/jquery.foundation.tabs.js
foundation/static/foundation/javascripts/jquery.foundation.tooltips.js
foundation/static/foundation/javascripts/jquery.foundation.topbar.js
