Metadata-Version: 1.1
Name: django-foundation
Version: 0.1
Summary: Django Integration with foundation front-end.
Home-page: https://github.com/petry/django-foundation
Author: Marcos Daniel Petry
Author-email: marcospetry@gmail.com
License: BSD License
Platform: UNKNOWN
Classifier: Environment :: Web Environment
Classifier: Framework :: Django
Classifier: Intended Audience :: Developers
Classifier: License :: OSI Approved :: BSD License
Classifier: Operating System :: OS Independent
Classifier: Programming Language :: Python
Classifier: Topic :: Utilities
